pyconf_ezload/__init__.py
pyconf_ezload/config_loader.py
pyconf_ezload-0.1.1.dist-info/LICENSE
pyconf_ezload-0.1.1.dist-info/METADATA
pyconf_ezload-0.1.1.dist-info/WHEEL
pyconf_ezload-0.1.1.dist-info/RECORD
