Metadata-Version: 2.3
Name: pyconf-ezload
Version: 0.1.1
Summary: A Python package for loading, validating, configurations from various sources.
License: MIT
Author: Kartikeya Malimath
Author-email: kartikeyapm@gmail.com
Requires-Python: >=3.9
Classifier: License :: OSI Approved :: MIT License
Classifier: Programming Language :: Python :: 3
Classifier: Programming Language :: Python :: 3.9
Classifier: Programming Language :: Python :: 3.10
Classifier: Programming Language :: Python :: 3.11
Classifier: Programming Language :: Python :: 3.12
Classifier: Programming Language :: Python :: 3.13
Requires-Dist: jsonschema (>=4.23.0,<5.0.0)
Requires-Dist: pydantic (>=2.11.1,<3.0.0)
Requires-Dist: pyyaml (>=6.0.2,<7.0.0)
Requires-Dist: watchdog (>=6.0.0,<7.0.0)
